nonebot_plugin_souti/__init__.py
nonebot_plugin_souti-1.0.1.dist-info/LICENSE
nonebot_plugin_souti-1.0.1.dist-info/METADATA
nonebot_plugin_souti-1.0.1.dist-info/WHEEL
nonebot_plugin_souti-1.0.1.dist-info/RECORD
