Metadata-Version: 2.1
Name: nonebot-plugin-souti
Version: 1.0.1
Summary: 基于 Nonebot2 的一款文字搜题插件
Home-page: https://github.com/xiaoWangSec/nonebot-plugin-souti
License: MPL2.0
Author: xiaoWangSec
Requires-Python: >=3.8,<4
Classifier: License :: Other/Proprietary License
Classifier: Programming Language :: Python :: 3
Classifier: Programming Language :: Python :: 3.8
Classifier: Programming Language :: Python :: 3.9
Classifier: Programming Language :: Python :: 3.10
Classifier: Programming Language :: Python :: 3.11
Requires-Dist: httpx (>=0.19.0)
Requires-Dist: nonebot2 (>=2.0.0-beta.1)
Project-URL: Repository, https://github.com/xiaoWangSec/nonebot-plugin-souti
